validata_api/__init__.py
validata_api/config.py
validata_api/json_errors.py
validata_api/route_handlers.py
Validata_API-0.7.4.dist-info/LICENSE
Validata_API-0.7.4.dist-info/METADATA
Validata_API-0.7.4.dist-info/WHEEL
Validata_API-0.7.4.dist-info/top_level.txt
Validata_API-0.7.4.dist-info/zip-safe
Validata_API-0.7.4.dist-info/RECORD
