Metadata-Version: 2.1
Name: Validata-API
Version: 0.7.4
Summary: Validata Web API
Home-page: https://git.opendatafrance.net/validata/validata-api
Author: Validata team
Author-email: admin-validata@jailbreak.paris
License: AGPLv3
Platform: UNKNOWN
Classifier: Development Status :: 5 - Production/Stable
Classifier: Intended Audience :: Developers
Classifier: Topic :: Software Development :: Libraries :: Python Modules
Classifier: Operating System :: OS Independent
Classifier: License :: OSI Approved :: GNU Affero General Public License v3
Classifier: Programming Language :: Python :: 3
License-File: LICENSE
Requires-Dist: apispec
Requires-Dist: cachetools
Requires-Dist: flask
Requires-Dist: flask-cors
Requires-Dist: flask-matomo
Requires-Dist: flasgger
Requires-Dist: marshmallow
Requires-Dist: python-dotenv
Requires-Dist: requests
Requires-Dist: toml
Requires-Dist: toolz
Requires-Dist: ujson
Requires-Dist: shapely
Requires-Dist: validata-core (==0.9.6)
